aprofiles/__init__.py
aprofiles/aeronet.py
aprofiles/cli/__init__.py
aprofiles/cli/apro.py
aprofiles/cli/config/cfg.json
aprofiles/cli/utils/__init__.py
aprofiles/cli/utils/calendar.py
aprofiles/cli/utils/climatology.py
aprofiles/cli/utils/config.py
aprofiles/cli/utils/l2b.py
aprofiles/cli/utils/map.py
aprofiles/cli/utils/workflow.py
aprofiles/config/aer_ifs.json
aprofiles/config/aer_properties.json
aprofiles/detection/__init__.py
aprofiles/detection/clouds.py
aprofiles/detection/foc.py
aprofiles/detection/ml_models/encoder.keras
aprofiles/detection/ml_models/kmeans.pkl
aprofiles/detection/pbl.py
aprofiles/io/__init__.py
aprofiles/io/read_aeronet.py
aprofiles/io/read_eprofile.py
aprofiles/io/write_profiles.py
aprofiles/mec.py
aprofiles/plot/__init__.py
aprofiles/plot/image.py
aprofiles/plot/profile.py
aprofiles/plot/timeseries.py
aprofiles/profiles.py
aprofiles/rayleigh.py
aprofiles/reader.py
aprofiles/retrieval/__init__.py
aprofiles/retrieval/extinction.py
aprofiles/retrieval/mass_conc.py
aprofiles/retrieval/ref_altitude.py
aprofiles/simulation/__init__.py
aprofiles/simulation/ext2back.py
aprofiles/size_distribution.py
aprofiles/utils.py
aprofiles-0.14.2.dist-info/LICENSE
aprofiles-0.14.2.dist-info/METADATA
aprofiles-0.14.2.dist-info/WHEEL
aprofiles-0.14.2.dist-info/entry_points.txt
aprofiles-0.14.2.dist-info/RECORD
