Metadata-Version: 2.3
Name: aprofiles
Version: 0.14.2
Summary: Analysis of atmospheric profilers measurements
License: GPL-3.0
Author: augustinm
Author-email: augustinm@met.no
Requires-Python: >=3.10,<3.13
Classifier: License :: OSI Approved :: GNU General Public License v3 (GPLv3)
Classifier: Programming Language :: Python :: 3
Classifier: Programming Language :: Python :: 3.10
Classifier: Programming Language :: Python :: 3.11
Classifier: Programming Language :: Python :: 3.12
Provides-Extra: cli
Provides-Extra: dev
Provides-Extra: docs
Requires-Dist: black (>=24.8.0,<25.0.0) ; extra == "dev"
Requires-Dist: dask (>=2024.9.0,<2025.0.0)
Requires-Dist: ipykernel (>=6.5.1,<7.0.0) ; extra == "dev"
Requires-Dist: ipython (>=8.27.0,<9.0.0) ; extra == "dev"
Requires-Dist: ipywidgets (>=8.1.5,<9.0.0) ; extra == "dev"
Requires-Dist: joblib (>=1.4.2,<2.0.0)
Requires-Dist: markdown-include (>=0.8.1,<0.9.0) ; extra == "docs"
Requires-Dist: matplotlib (>=3.8.0,<3.9)
Requires-Dist: miepython (>=2.2.1,<3.0.0)
Requires-Dist: mkdocs-autorefs (>=1.3.0,<2.0.0) ; extra == "docs"
Requires-Dist: mkdocs-copy (>=0.0.1,<0.0.2) ; extra == "docs"
Requires-Dist: mkdocs-material (>=9.6.2,<10.0.0) ; extra == "docs"
Requires-Dist: mkdocstrings (>=0.28.0,<0.29.0) ; extra == "docs"
Requires-Dist: mkdocstrings-python (>=1.14.3,<2.0.0) ; extra == "docs"
Requires-Dist: netCDF4 (>=1.5.8,<2.0.0)
Requires-Dist: numba (>=0.60.0,<0.61.0)
Requires-Dist: numpy (>=1.22,<2.1)
Requires-Dist: orjson (>=3.10.7,<4.0.0)
Requires-Dist: pymdown-extensions (>=10.10,<11.0) ; extra == "dev"
Requires-Dist: pytest (>=8.3.3,<9.0.0) ; extra == "dev"
Requires-Dist: pytest-cov (>=3.0.0,<4.0.0) ; extra == "dev"
Requires-Dist: rich (>=13.8.1,<14.0.0)
Requires-Dist: scikit-image (>=0.25.1,<0.26.0)
Requires-Dist: scikit-learn (>=1.6.1,<2.0.0)
Requires-Dist: scipy (>=1.7.2,<2.0.0)
Requires-Dist: seaborn (>=0.13.0,<0.14.0)
Requires-Dist: tensorflow (>=2.18.0,<3.0.0)
Requires-Dist: typer (>=0.15.1,<0.16.0) ; extra == "cli"
Requires-Dist: xarray (>=v2024.09.0,<2025.0.0)
